{
  "_fv": 13,
  "_type": "dimension",
  "definition": {
    "portalFrame": {
      "value": "CUSTOM:AsphaltBlock"
    },
    "portalParticles": {
      "value": "EXPLOSION_NORMAL"
    },
    "portalLuminance": 0.0,
    "portalSound": {
      "value": "block.portal.ambient"
    },
    "igniterName": "Dark_Essence",
    "igniterTab": {
      "value": "TOOLS"
    },
    "texture": "prismarine_cutlass",
    "portalTexture": "glowshroom_block",
    "enablePortal": true,
    "biomesInDimension": [
      {
        "value": "CUSTOM:DarkPlains"
      }
    ],
    "worldGenType": "Nether like gen",
    "mainFillerBlock": {
      "value": "CUSTOM:AsphaltBlock"
    },
    "fluidBlock": {
      "value": "CUSTOM:DarkJuice"
    },
    "airColor": {
      "value": -16777216,
      "falpha": 0.0
    },
    "canRespawnHere": true,
    "hasFog": true,
    "hasWeather": false,
    "isDark": true,
    "doesWaterVaporize": true,
    "sleepResult": "BED_EXPLODES",
    "hasSkyLight": false,
    "imitateOverworldBehaviour": false
  }
}