{
  "_fv": 13,
  "_type": "structure",
  "definition": {
    "structure": "rwblock3",
    "randomlyRotateStructure": true,
    "surfaceDetectionType": "First motion blocking block",
    "spawnProbability": 1000000,
    "minCountPerChunk": 1,
    "maxCountPerChunk": 1,
    "spawnLocation": "Ground",
    "spawnHeightOffset": 1,
    "spawnXOffset": 0,
    "spawnZOffset": 0,
    "spawnWorldTypes": [
      "Surface"
    ],
    "restrictionBlocks": [
      {
        "value": "Blocks.GRASS"
      }
    ],
    "restrictionBiomes": [
      {
        "value": "CUSTOM:AlpineBorder"
      }
    ],
    "ignoreBlocks": "STRUCTURE_BLOCK",
    "onStructureGenerated": {
      "name": "Rw3spawnblock"
    }
  }
}