{
  "_fv": 13,
  "_type": "gui",
  "definition": {
    "type": 1,
    "width": 176,
    "height": 170,
    "inventoryOffsetX": 0,
    "inventoryOffsetY": 0,
    "renderBgLayer": true,
    "doesPauseGame": false,
    "components": [
      {
        "type": "label",
        "data": {
          "text": "Lamberjack",
          "color": {
            "value": -6710887,
            "falpha": 0.0
          },
          "name": "Lamberjack",
          "x": 189,
          "y": 45
        }
      },
      {
        "type": "inputslot",
        "data": {
          "inputLimit": {
            "value": ""
          },
          "id": 0,
          "disableStackInteraction": false,
          "dropItemsWhenNotBound": true,
          "onSlotChanged": {
            "name": "TimbermanExchange"
          },
          "name": "Slot #0",
          "x": 151,
          "y": 85
        }
      },
      {
        "type": "outputslot",
        "data": {
          "id": 1,
          "disableStackInteraction": false,
          "dropItemsWhenNotBound": true,
          "name": "Slot #1",
          "x": 258,
          "y": 85
        }
      },
      {
        "type": "label",
        "data": {
          "text": "Input The Item",
          "color": {
            "value": -1,
            "falpha": 0.0
          },
          "name": "Input The Item",
          "x": 137,
          "y": 64
        }
      }
    ]
  }
}